efk_log/__init__.py
efk_log/log_format.py
efk_log/logger_json.py
efk_log-1.0.1.dist-info/METADATA
efk_log-1.0.1.dist-info/WHEEL
efk_log-1.0.1.dist-info/RECORD
